CHANGELOG.md
MANIFEST.in
Procfile
README.rst
config.ini
local.ini
main.py
requirements.txt
runtime.txt
setup.cfg
setup.py
skeleton.py
swagger.yaml
ons_ras_common/__init__.py
ons_ras_common/ons_cloudfoundry.py
ons_ras_common/ons_cryptographer.py
ons_ras_common/ons_database.py
ons_ras_common/ons_decorators.py
ons_ras_common/ons_environment.py
ons_ras_common/ons_jwt.py
ons_ras_common/ons_logger.py
ons_ras_common/ons_registration.py
ons_ras_common/ons_swagger.py
ons_ras_common/ons_tool.py
ons_ras_common.egg-info/PKG-INFO
ons_ras_common.egg-info/SOURCES.txt
ons_ras_common.egg-info/dependency_links.txt
ons_ras_common.egg-info/entry_points.txt
ons_ras_common.egg-info/requires.txt
ons_ras_common.egg-info/top_level.txt