Metadata-Version: 1.1
Name: ons-ras-common
Version: 0.1.15
Summary: The Common library for ONS RAS Micro-Services
Home-page: https://github.com/ONSdigital/ras-common
Author: RAS Development Team
Author-email: onsdigital@linux.co.uk
License: MIT
Keywords: micro-service,ons-ras
Platform: UNKNOWN
Classifier: Development Status :: 3 - Alpha
Classifier: Intended Audience :: Developers
Classifier: Topic :: Software Development :: Build Tools
Classifier: License :: OSI Approved :: MIT License
Classifier: Programming Language :: Python :: 3.5
Classifier: Programming Language :: Python :: 3.6
